{
  "$schema": "https://developer.microsoft.com/json-schemas/fabric/item/report/definition/visualContainer/2.3.0/schema.json",
  "name": "0bfa6c7938e7aa008eb1",
  "position": {
    "x": 1326.31681506942,
    "y": 18.706866221007335,
    "z": 8005,
    "height": 92.598987793986311,
    "width": 291.82711304771442,
    "tabOrder": 8005
  },
  "visual": {
    "visualType": "slicer",
    "query": {
      "queryState": {
        "Values": {
          "projections": [
            {
              "field": {
                "Column": {
                  "Expression": {
                    "SourceRef": {
                      "Entity": "Dates"
                    }
                  },
                  "Property": "Date"
                }
              },
              "queryRef": "Dates.Date",
              "nativeQueryRef": "Date",
              "active": true
            }
          ]
        }
      },
      "sortDefinition": {
        "sort": [
          {
            "field": {
              "Column": {
                "Expression": {
                  "SourceRef": {
                    "Entity": "Dates"
                  }
                },
                "Property": "Date"
              }
            },
            "direction": "Ascending"
          }
        ],
        "isDefaultSort": true
      }
    },
    "objects": {
      "data": [
        {
          "properties": {
            "startDate": {
              "expr": {
                "Literal": {
                  "Value": "datetime'2025-01-07T00:00:00'"
                }
              }
            },
            "endDate": {
              "expr": {
                "Literal": {
                  "Value": "datetime'2025-10-23T01:00:00'"
                }
              }
            },
            "mode": {
              "expr": {
                "Literal": {
                  "Value": "'Between'"
                }
              }
            }
          }
        }
      ],
      "general": [
        {
          "properties": {
            "filter": {
              "filter": {
                "Version": 2,
                "From": [
                  {
                    "Name": "d",
                    "Entity": "Dates",
                    "Type": 0
                  }
                ],
                "Where": [
                  {
                    "Condition": {
                      "And": {
                        "Left": {
                          "Comparison": {
                            "ComparisonKind": 2,
                            "Left": {
                              "Column": {
                                "Expression": {
                                  "SourceRef": {
                                    "Source": "d"
                                  }
                                },
                                "Property": "Date"
                              }
                            },
                            "Right": {
                              "Literal": {
                                "Value": "datetime'2025-01-07T00:00:00'"
                              }
                            }
                          }
                        },
                        "Right": {
                          "Comparison": {
                            "ComparisonKind": 3,
                            "Left": {
                              "Column": {
                                "Expression": {
                                  "SourceRef": {
                                    "Source": "d"
                                  }
                                },
                                "Property": "Date"
                              }
                            },
                            "Right": {
                              "Literal": {
                                "Value": "datetime'2025-10-24T00:00:00'"
                              }
                            }
                          }
                        }
                      }
                    }
                  }
                ]
              }
            }
          }
        }
      ]
    },
    "visualContainerObjects": {
      "title": [
        {
          "properties": {
            "titleWrap": {
              "expr": {
                "Literal": {
                  "Value": "true"
                }
              }
            }
          }
        }
      ],
      "background": [
        {
          "properties": {
            "show": {
              "expr": {
                "Literal": {
                  "Value": "true"
                }
              }
            },
            "transparency": {
              "expr": {
                "Literal": {
                  "Value": "0D"
                }
              }
            }
          }
        }
      ],
      "border": [
        {
          "properties": {
            "width": {
              "expr": {
                "Literal": {
                  "Value": "1D"
                }
              }
            }
          }
        }
      ]
    },
    "drillFilterOtherVisuals": true
  }
}